{
  "project_info": {
    "project_number": "694548197000",
    "project_id": "look-e96f3",
    "storage_bucket": "look-e96f3.appspot.com"
  },
  "client": [
    {
      "client_info": {
        "mobilesdk_app_id": "1:694548197000:android:76b9121c411388c1adb93d",
        "android_client_info": {
          "package_name": "com.example.sharedpref"
        }
      },
      "oauth_client": [
        {
          "client_id": "694548197000-kk3r9l0v25c3bloc7oikbaedatr3kc86.apps.googleusercontent.com",
          "client_type": 3
        }
      ],
      "api_key": [
        {
          "current_key": "AIzaSyAu-myoKEeCS88tMqqSPCbmDNDNSrgNVqM"
        }
      ],
      "services": {
        "appinvite_service": {
          "other_platform_oauth_client": [
            {
              "client_id": "694548197000-kk3r9l0v25c3bloc7oikbaedatr3kc86.apps.googleusercontent.com",
              "client_type": 3
            }
          ]
        }
      }
    }
  ],
  "configuration_version": "1"
}